Metadata-Version: 2.1
Name: hpscancli
Version: 1.0.0
Summary: A simple python CLI tool to connect to HP scanner devices over local network and scan documents with ease.
Home-page: https://github.com/prasannareddych/HPScanCLI
Author: Prasanna Reddy. Ch
Author-email: prasannareddy_ch@outlook.com
Classifier: Programming Language :: Python :: 3
Classifier: License :: OSI Approved :: MIT License
Classifier: Operating System :: OS Independent
Requires-Python: >=3.6
License-File: LICENSE
Requires-Dist: bs4
Requires-Dist: requests
